savior/__init__.py
savior-0.2.3.dist-info/LICENSE
savior-0.2.3.dist-info/METADATA
savior-0.2.3.dist-info/WHEEL
savior-0.2.3.dist-info/top_level.txt
savior-0.2.3.dist-info/RECORD
