Metadata-Version: 2.1
Name: savior
Version: 0.2.3
Summary: Flexible immutable entity database
Home-page: https://gitlab.com/elibdev/savior
Author: Eli B
Author-email: eli@formal.studio
License: ISC
Platform: UNKNOWN
Classifier: License :: OSI Approved :: ISC License (ISCL)
Classifier: Programming Language :: Python :: 3
Classifier: Programming Language :: Python :: 3.7
Requires-Dist: lmdb
Requires-Dist: msgpack
